{
"type": "FeatureCollection",
"name": "attractions",
"crs": { "type": "name", "properties": { "name": "urn:ogc:def:crs:OGC:1.3:CRS84" } },
"features": [
{ "type": "Feature", "properties": { "id": 1, "Name": "גבעות", "info": "כלום" }, "geometry": { "type": "Point", "coordinates": [ 35.101284241601853, 31.679156368981012 ] } },
{ "type": "Feature", "properties": { "id": 2, "Name": "ראש צורים", "info": null }, "geometry": { "type": "Point", "coordinates": [ 35.126003795820637, 31.667563248730211 ] } }
]
}
